<?xml version="1.0"?>
<duseed>
  <deploymentUnit id="crystalreports.cpp.businessview.clients.crw-4.0-core-32" revision="14.0.4.738" schemaVersion="3" packagedOnPlatform="win32_x86" installiverseId="aurora" sizeInCache="1744455">
    <requiredDeploymentUnit ref="crystalreports.cpp.businessview.sdk-4.0-core"/>
    <requiredDeploymentUnit ref="setup.core-4.0-core"/>
  </deploymentUnit>
  <uninstall>
    <action id="UninstallDUBundle">
      <arg name="guid" value="FC9A8F8E-B5D4-4AED-B463-E7E0FB559155"/>
      <arg name="Props" value="INSTALLDIR=&quot;[INSTALLDIR]&quot;"/>
    </action>
  </uninstall>
  <install>
    <action id="InstallDUBundle">
      <arg name="Props" value="INSTALLDIR=&quot;[INSTALLDIR]&quot;"/>
    </action>
  </install>
</duseed>
